{
    "generated_local":  "2026-06-15T11:40:53",
    "active_power_plan":  {
                              "guid":  "692ee1d0-ffc2-4c47-91b3-2a4814f3964e",
                              "name":  "AERO24_MODERATE_AGGRESSIVE_GAMING",
                              "raw":  "Power Scheme GUID: 692ee1d0-ffc2-4c47-91b3-2a4814f3964e  (AERO24_MODERATE_AGGRESSIVE_GAMING)"
                          },
    "active_power_plan_export_path":  "C:\\Users\\kkids\\Documents\\Codex_Computer_Optimizing\\AERO_X16_CONTROL_CENTER_APP\\PHASE_4_BACKUP_RESTORE_FOUNDATION_AND_SANDBOXED_APPLY_TESTS\\backups\\power_plans\\active_power_plan_20260615-114052.pow",
    "full_query_stdout_path":  "C:\\Users\\kkids\\Documents\\Codex_Computer_Optimizing\\AERO_X16_CONTROL_CENTER_APP\\PHASE_4_BACKUP_RESTORE_FOUNDATION_AND_SANDBOXED_APPLY_TESTS\\raw_outputs\\power_plan_backup\\powercfg_query_scheme_current_full_stdout.txt",
    "processor_query_stdout_path":  "C:\\Users\\kkids\\Documents\\Codex_Computer_Optimizing\\AERO_X16_CONTROL_CENTER_APP\\PHASE_4_BACKUP_RESTORE_FOUNDATION_AND_SANDBOXED_APPLY_TESTS\\raw_outputs\\power_plan_backup\\powercfg_query_scheme_current_processor_stdout.txt",
    "cpu_settings":  [
                         {
                             "control_id":  "cpu.boost.mode",
                             "friendly_name":  "Processor performance boost mode",
                             "alias":  "PERFBOOSTMODE",
                             "setting_guid":  "be337238-0d82-4146-a960-4f3749d470c7",
                             "readable":  true,
                             "ac_value":  0,
                             "dc_value":  2,
                             "ac_hex":  "0x00000000",
                             "dc_hex":  "0x00000002",
                             "command":  {
                                             "name":  "powercfg_query_active_PERFBOOSTMODE",
                                             "command":  [
                                                             "powercfg.exe",
                                                             "/query",
                                                             "SCHEME_CURRENT",
                                                             "SUB_PROCESSOR",
                                                             "be337238-0d82-4146-a960-4f3749d470c7"
                                                         ],
                                             "exit_code":  0,
                                             "stdout_path":  "C:\\Users\\kkids\\Documents\\Codex_Computer_Optimizing\\AERO_X16_CONTROL_CENTER_APP\\PHASE_4_BACKUP_RESTORE_FOUNDATION_AND_SANDBOXED_APPLY_TESTS\\raw_outputs\\power_plan_backup\\powercfg_query_active_PERFBOOSTMODE_stdout.txt",
                                             "stderr_path":  "C:\\Users\\kkids\\Documents\\Codex_Computer_Optimizing\\AERO_X16_CONTROL_CENTER_APP\\PHASE_4_BACKUP_RESTORE_FOUNDATION_AND_SANDBOXED_APPLY_TESTS\\raw_outputs\\power_plan_backup\\powercfg_query_active_PERFBOOSTMODE_stderr.txt",
                                             "stdout":  "Power Scheme GUID: 692ee1d0-ffc2-4c47-91b3-2a4814f3964e  (AERO24_MODERATE_AGGRESSIVE_GAMING)\r\n  Subgroup GUID: 54533251-82be-4824-96c1-47b60b740d00  (Processor power management)\r\n    GUID Alias: SUB_PROCESSOR\r\n    Power Setting GUID: be337238-0d82-4146-a960-4f3749d470c7  (Processor performance boost mode)\r\n      GUID Alias: PERFBOOSTMODE\r\n      Possible Setting Index: 000\r\n      Possible Setting Friendly Name: Disabled\r\n      Possible Setting Index: 001\r\n      Possible Setting Friendly Name: Enabled\r\n      Possible Setting Index: 002\r\n      Possible Setting Friendly Name: Aggressive\r\n      Possible Setting Index: 003\r\n      Possible Setting Friendly Name: Efficient Enabled\r\n      Possible Setting Index: 004\r\n      Possible Setting Friendly Name: Efficient Aggressive\r\n      Possible Setting Index: 005\r\n      Possible Setting Friendly Name: Aggressive At Guaranteed\r\n      Possible Setting Index: 006\r\n      Possible Setting Friendly Name: Efficient Aggressive At Guaranteed\r\n    Current AC Power Setting Index: 0x00000000\r\n    Current DC Power Setting Index: 0x00000002",
                                             "stderr":  "",
                                             "error":  null,
                                             "started_at":  "2026-06-15T11:40:53",
                                             "completed_at":  "2026-06-15T11:40:53"
                                         }
                         },
                         {
                             "control_id":  "cpu.boost.policy",
                             "friendly_name":  "Processor performance boost policy",
                             "alias":  "PERFBOOSTPOL",
                             "setting_guid":  "45bcc044-d885-43e2-8605-ee0ec6e96b59",
                             "readable":  false,
                             "ac_value":  null,
                             "dc_value":  null,
                             "ac_hex":  null,
                             "dc_hex":  null,
                             "command":  {
                                             "name":  "powercfg_query_active_PERFBOOSTPOL",
                                             "command":  [
                                                             "powercfg.exe",
                                                             "/query",
                                                             "SCHEME_CURRENT",
                                                             "SUB_PROCESSOR",
                                                             "45bcc044-d885-43e2-8605-ee0ec6e96b59"
                                                         ],
                                             "exit_code":  0,
                                             "stdout_path":  "C:\\Users\\kkids\\Documents\\Codex_Computer_Optimizing\\AERO_X16_CONTROL_CENTER_APP\\PHASE_4_BACKUP_RESTORE_FOUNDATION_AND_SANDBOXED_APPLY_TESTS\\raw_outputs\\power_plan_backup\\powercfg_query_active_PERFBOOSTPOL_stdout.txt",
                                             "stderr_path":  "C:\\Users\\kkids\\Documents\\Codex_Computer_Optimizing\\AERO_X16_CONTROL_CENTER_APP\\PHASE_4_BACKUP_RESTORE_FOUNDATION_AND_SANDBOXED_APPLY_TESTS\\raw_outputs\\power_plan_backup\\powercfg_query_active_PERFBOOSTPOL_stderr.txt",
                                             "stdout":  "Power Scheme GUID: 692ee1d0-ffc2-4c47-91b3-2a4814f3964e  (AERO24_MODERATE_AGGRESSIVE_GAMING)",
                                             "stderr":  "",
                                             "error":  null,
                                             "started_at":  "2026-06-15T11:40:53",
                                             "completed_at":  "2026-06-15T11:40:53"
                                         }
                         },
                         {
                             "control_id":  "cpu.power.epp",
                             "friendly_name":  "Processor energy performance preference / EPP",
                             "alias":  "PERFEPP",
                             "setting_guid":  "36687f9e-e3a5-4dbf-b1dc-15eb381c6863",
                             "readable":  true,
                             "ac_value":  55,
                             "dc_value":  0,
                             "ac_hex":  "0x00000037",
                             "dc_hex":  "0x00000000",
                             "command":  {
                                             "name":  "powercfg_query_active_PERFEPP",
                                             "command":  [
                                                             "powercfg.exe",
                                                             "/query",
                                                             "SCHEME_CURRENT",
                                                             "SUB_PROCESSOR",
                                                             "36687f9e-e3a5-4dbf-b1dc-15eb381c6863"
                                                         ],
                                             "exit_code":  0,
                                             "stdout_path":  "C:\\Users\\kkids\\Documents\\Codex_Computer_Optimizing\\AERO_X16_CONTROL_CENTER_APP\\PHASE_4_BACKUP_RESTORE_FOUNDATION_AND_SANDBOXED_APPLY_TESTS\\raw_outputs\\power_plan_backup\\powercfg_query_active_PERFEPP_stdout.txt",
                                             "stderr_path":  "C:\\Users\\kkids\\Documents\\Codex_Computer_Optimizing\\AERO_X16_CONTROL_CENTER_APP\\PHASE_4_BACKUP_RESTORE_FOUNDATION_AND_SANDBOXED_APPLY_TESTS\\raw_outputs\\power_plan_backup\\powercfg_query_active_PERFEPP_stderr.txt",
                                             "stdout":  "Power Scheme GUID: 692ee1d0-ffc2-4c47-91b3-2a4814f3964e  (AERO24_MODERATE_AGGRESSIVE_GAMING)\r\n  Subgroup GUID: 54533251-82be-4824-96c1-47b60b740d00  (Processor power management)\r\n    GUID Alias: SUB_PROCESSOR\r\n    Power Setting GUID: 36687f9e-e3a5-4dbf-b1dc-15eb381c6863  (Processor energy performance preference policy)\r\n      GUID Alias: PERFEPP\r\n      Minimum Possible Setting: 0x00000000\r\n      Maximum Possible Setting: 0x00000064\r\n      Possible Settings increment: 0x00000001\r\n      Possible Settings units: %\r\n    Current AC Power Setting Index: 0x00000037\r\n    Current DC Power Setting Index: 0x00000000",
                                             "stderr":  "",
                                             "error":  null,
                                             "started_at":  "2026-06-15T11:40:53",
                                             "completed_at":  "2026-06-15T11:40:53"
                                         }
                         },
                         {
                             "control_id":  "cpu.state.minimum",
                             "friendly_name":  "Minimum processor state",
                             "alias":  "PROCTHROTTLEMIN",
                             "setting_guid":  "893dee8e-2bef-41e0-89c6-b55d0929964c",
                             "readable":  true,
                             "ac_value":  5,
                             "dc_value":  100,
                             "ac_hex":  "0x00000005",
                             "dc_hex":  "0x00000064",
                             "command":  {
                                             "name":  "powercfg_query_active_PROCTHROTTLEMIN",
                                             "command":  [
                                                             "powercfg.exe",
                                                             "/query",
                                                             "SCHEME_CURRENT",
                                                             "SUB_PROCESSOR",
                                                             "893dee8e-2bef-41e0-89c6-b55d0929964c"
                                                         ],
                                             "exit_code":  0,
                                             "stdout_path":  "C:\\Users\\kkids\\Documents\\Codex_Computer_Optimizing\\AERO_X16_CONTROL_CENTER_APP\\PHASE_4_BACKUP_RESTORE_FOUNDATION_AND_SANDBOXED_APPLY_TESTS\\raw_outputs\\power_plan_backup\\powercfg_query_active_PROCTHROTTLEMIN_stdout.txt",
                                             "stderr_path":  "C:\\Users\\kkids\\Documents\\Codex_Computer_Optimizing\\AERO_X16_CONTROL_CENTER_APP\\PHASE_4_BACKUP_RESTORE_FOUNDATION_AND_SANDBOXED_APPLY_TESTS\\raw_outputs\\power_plan_backup\\powercfg_query_active_PROCTHROTTLEMIN_stderr.txt",
                                             "stdout":  "Power Scheme GUID: 692ee1d0-ffc2-4c47-91b3-2a4814f3964e  (AERO24_MODERATE_AGGRESSIVE_GAMING)\r\n  Subgroup GUID: 54533251-82be-4824-96c1-47b60b740d00  (Processor power management)\r\n    GUID Alias: SUB_PROCESSOR\r\n    Power Setting GUID: 893dee8e-2bef-41e0-89c6-b55d0929964c  (Minimum processor state)\r\n      GUID Alias: PROCTHROTTLEMIN\r\n      Minimum Possible Setting: 0x00000000\r\n      Maximum Possible Setting: 0x00000064\r\n      Possible Settings increment: 0x00000001\r\n      Possible Settings units: %\r\n    Current AC Power Setting Index: 0x00000005\r\n    Current DC Power Setting Index: 0x00000064",
                                             "stderr":  "",
                                             "error":  null,
                                             "started_at":  "2026-06-15T11:40:53",
                                             "completed_at":  "2026-06-15T11:40:53"
                                         }
                         },
                         {
                             "control_id":  "cpu.state.maximum",
                             "friendly_name":  "Maximum processor state",
                             "alias":  "PROCTHROTTLEMAX",
                             "setting_guid":  "bc5038f7-23e0-4960-96da-33abaf5935ec",
                             "readable":  true,
                             "ac_value":  99,
                             "dc_value":  100,
                             "ac_hex":  "0x00000063",
                             "dc_hex":  "0x00000064",
                             "command":  {
                                             "name":  "powercfg_query_active_PROCTHROTTLEMAX",
                                             "command":  [
                                                             "powercfg.exe",
                                                             "/query",
                                                             "SCHEME_CURRENT",
                                                             "SUB_PROCESSOR",
                                                             "bc5038f7-23e0-4960-96da-33abaf5935ec"
                                                         ],
                                             "exit_code":  0,
                                             "stdout_path":  "C:\\Users\\kkids\\Documents\\Codex_Computer_Optimizing\\AERO_X16_CONTROL_CENTER_APP\\PHASE_4_BACKUP_RESTORE_FOUNDATION_AND_SANDBOXED_APPLY_TESTS\\raw_outputs\\power_plan_backup\\powercfg_query_active_PROCTHROTTLEMAX_stdout.txt",
                                             "stderr_path":  "C:\\Users\\kkids\\Documents\\Codex_Computer_Optimizing\\AERO_X16_CONTROL_CENTER_APP\\PHASE_4_BACKUP_RESTORE_FOUNDATION_AND_SANDBOXED_APPLY_TESTS\\raw_outputs\\power_plan_backup\\powercfg_query_active_PROCTHROTTLEMAX_stderr.txt",
                                             "stdout":  "Power Scheme GUID: 692ee1d0-ffc2-4c47-91b3-2a4814f3964e  (AERO24_MODERATE_AGGRESSIVE_GAMING)\r\n  Subgroup GUID: 54533251-82be-4824-96c1-47b60b740d00  (Processor power management)\r\n    GUID Alias: SUB_PROCESSOR\r\n    Power Setting GUID: bc5038f7-23e0-4960-96da-33abaf5935ec  (Maximum processor state)\r\n      GUID Alias: PROCTHROTTLEMAX\r\n      Minimum Possible Setting: 0x00000000\r\n      Maximum Possible Setting: 0x00000064\r\n      Possible Settings increment: 0x00000001\r\n      Possible Settings units: %\r\n    Current AC Power Setting Index: 0x00000063\r\n    Current DC Power Setting Index: 0x00000064",
                                             "stderr":  "",
                                             "error":  null,
                                             "started_at":  "2026-06-15T11:40:53",
                                             "completed_at":  "2026-06-15T11:40:53"
                                         }
                         },
                         {
                             "control_id":  "cpu.cooling.system_policy",
                             "friendly_name":  "System cooling policy",
                             "alias":  "SYSCOOLPOL",
                             "setting_guid":  "94d3a615-a899-4ac5-ae2b-e4d8f634367f",
                             "readable":  true,
                             "ac_value":  1,
                             "dc_value":  1,
                             "ac_hex":  "0x00000001",
                             "dc_hex":  "0x00000001",
                             "command":  {
                                             "name":  "powercfg_query_active_SYSCOOLPOL",
                                             "command":  [
                                                             "powercfg.exe",
                                                             "/query",
                                                             "SCHEME_CURRENT",
                                                             "SUB_PROCESSOR",
                                                             "94d3a615-a899-4ac5-ae2b-e4d8f634367f"
                                                         ],
                                             "exit_code":  0,
                                             "stdout_path":  "C:\\Users\\kkids\\Documents\\Codex_Computer_Optimizing\\AERO_X16_CONTROL_CENTER_APP\\PHASE_4_BACKUP_RESTORE_FOUNDATION_AND_SANDBOXED_APPLY_TESTS\\raw_outputs\\power_plan_backup\\powercfg_query_active_SYSCOOLPOL_stdout.txt",
                                             "stderr_path":  "C:\\Users\\kkids\\Documents\\Codex_Computer_Optimizing\\AERO_X16_CONTROL_CENTER_APP\\PHASE_4_BACKUP_RESTORE_FOUNDATION_AND_SANDBOXED_APPLY_TESTS\\raw_outputs\\power_plan_backup\\powercfg_query_active_SYSCOOLPOL_stderr.txt",
                                             "stdout":  "Power Scheme GUID: 692ee1d0-ffc2-4c47-91b3-2a4814f3964e  (AERO24_MODERATE_AGGRESSIVE_GAMING)\r\n  Subgroup GUID: 54533251-82be-4824-96c1-47b60b740d00  (Processor power management)\r\n    GUID Alias: SUB_PROCESSOR\r\n    Power Setting GUID: 94d3a615-a899-4ac5-ae2b-e4d8f634367f  (System cooling policy)\r\n      GUID Alias: SYSCOOLPOL\r\n      Possible Setting Index: 000\r\n      Possible Setting Friendly Name: Passive\r\n      Possible Setting Index: 001\r\n      Possible Setting Friendly Name: Active\r\n    Current AC Power Setting Index: 0x00000001\r\n    Current DC Power Setting Index: 0x00000001",
                                             "stderr":  "",
                                             "error":  null,
                                             "started_at":  "2026-06-15T11:40:53",
                                             "completed_at":  "2026-06-15T11:40:53"
                                         }
                         },
                         {
                             "control_id":  "cpu.frequency.maximum",
                             "friendly_name":  "Maximum processor frequency",
                             "alias":  "PROCFREQMAX",
                             "setting_guid":  "75b0ae3f-bce0-45a7-8c89-c9611c25e100",
                             "readable":  true,
                             "ac_value":  3250,
                             "dc_value":  0,
                             "ac_hex":  "0x00000cb2",
                             "dc_hex":  "0x00000000",
                             "command":  {
                                             "name":  "powercfg_query_active_PROCFREQMAX",
                                             "command":  [
                                                             "powercfg.exe",
                                                             "/query",
                                                             "SCHEME_CURRENT",
                                                             "SUB_PROCESSOR",
                                                             "75b0ae3f-bce0-45a7-8c89-c9611c25e100"
                                                         ],
                                             "exit_code":  0,
                                             "stdout_path":  "C:\\Users\\kkids\\Documents\\Codex_Computer_Optimizing\\AERO_X16_CONTROL_CENTER_APP\\PHASE_4_BACKUP_RESTORE_FOUNDATION_AND_SANDBOXED_APPLY_TESTS\\raw_outputs\\power_plan_backup\\powercfg_query_active_PROCFREQMAX_stdout.txt",
                                             "stderr_path":  "C:\\Users\\kkids\\Documents\\Codex_Computer_Optimizing\\AERO_X16_CONTROL_CENTER_APP\\PHASE_4_BACKUP_RESTORE_FOUNDATION_AND_SANDBOXED_APPLY_TESTS\\raw_outputs\\power_plan_backup\\powercfg_query_active_PROCFREQMAX_stderr.txt",
                                             "stdout":  "Power Scheme GUID: 692ee1d0-ffc2-4c47-91b3-2a4814f3964e  (AERO24_MODERATE_AGGRESSIVE_GAMING)\r\n  Subgroup GUID: 54533251-82be-4824-96c1-47b60b740d00  (Processor power management)\r\n    GUID Alias: SUB_PROCESSOR\r\n    Power Setting GUID: 75b0ae3f-bce0-45a7-8c89-c9611c25e100  (Maximum processor frequency)\r\n      GUID Alias: PROCFREQMAX\r\n      Minimum Possible Setting: 0x00000000\r\n      Maximum Possible Setting: 0xffffffff\r\n      Possible Settings increment: 0x00000001\r\n      Possible Settings units: MHz\r\n    Current AC Power Setting Index: 0x00000cb2\r\n    Current DC Power Setting Index: 0x00000000",
                                             "stderr":  "",
                                             "error":  null,
                                             "started_at":  "2026-06-15T11:40:53",
                                             "completed_at":  "2026-06-15T11:40:53"
                                         }
                         },
                         {
                             "control_id":  "cpu.parking.min_cores",
                             "friendly_name":  "Processor performance core parking min cores",
                             "alias":  "CPMINCORES",
                             "setting_guid":  "0cc5b647-c1df-4637-891a-dec35c318583",
                             "readable":  false,
                             "ac_value":  null,
                             "dc_value":  null,
                             "ac_hex":  null,
                             "dc_hex":  null,
                             "command":  {
                                             "name":  "powercfg_query_active_CPMINCORES",
                                             "command":  [
                                                             "powercfg.exe",
                                                             "/query",
                                                             "SCHEME_CURRENT",
                                                             "SUB_PROCESSOR",
                                                             "0cc5b647-c1df-4637-891a-dec35c318583"
                                                         ],
                                             "exit_code":  0,
                                             "stdout_path":  "C:\\Users\\kkids\\Documents\\Codex_Computer_Optimizing\\AERO_X16_CONTROL_CENTER_APP\\PHASE_4_BACKUP_RESTORE_FOUNDATION_AND_SANDBOXED_APPLY_TESTS\\raw_outputs\\power_plan_backup\\powercfg_query_active_CPMINCORES_stdout.txt",
                                             "stderr_path":  "C:\\Users\\kkids\\Documents\\Codex_Computer_Optimizing\\AERO_X16_CONTROL_CENTER_APP\\PHASE_4_BACKUP_RESTORE_FOUNDATION_AND_SANDBOXED_APPLY_TESTS\\raw_outputs\\power_plan_backup\\powercfg_query_active_CPMINCORES_stderr.txt",
                                             "stdout":  "Power Scheme GUID: 692ee1d0-ffc2-4c47-91b3-2a4814f3964e  (AERO24_MODERATE_AGGRESSIVE_GAMING)",
                                             "stderr":  "",
                                             "error":  null,
                                             "started_at":  "2026-06-15T11:40:53",
                                             "completed_at":  "2026-06-15T11:40:53"
                                         }
                         },
                         {
                             "control_id":  "cpu.parking.max_cores",
                             "friendly_name":  "Processor performance core parking max cores",
                             "alias":  "CPMAXCORES",
                             "setting_guid":  "ea062031-0e34-4ff1-9b6d-eb1059334028",
                             "readable":  false,
                             "ac_value":  null,
                             "dc_value":  null,
                             "ac_hex":  null,
                             "dc_hex":  null,
                             "command":  {
                                             "name":  "powercfg_query_active_CPMAXCORES",
                                             "command":  [
                                                             "powercfg.exe",
                                                             "/query",
                                                             "SCHEME_CURRENT",
                                                             "SUB_PROCESSOR",
                                                             "ea062031-0e34-4ff1-9b6d-eb1059334028"
                                                         ],
                                             "exit_code":  0,
                                             "stdout_path":  "C:\\Users\\kkids\\Documents\\Codex_Computer_Optimizing\\AERO_X16_CONTROL_CENTER_APP\\PHASE_4_BACKUP_RESTORE_FOUNDATION_AND_SANDBOXED_APPLY_TESTS\\raw_outputs\\power_plan_backup\\powercfg_query_active_CPMAXCORES_stdout.txt",
                                             "stderr_path":  "C:\\Users\\kkids\\Documents\\Codex_Computer_Optimizing\\AERO_X16_CONTROL_CENTER_APP\\PHASE_4_BACKUP_RESTORE_FOUNDATION_AND_SANDBOXED_APPLY_TESTS\\raw_outputs\\power_plan_backup\\powercfg_query_active_CPMAXCORES_stderr.txt",
                                             "stdout":  "Power Scheme GUID: 692ee1d0-ffc2-4c47-91b3-2a4814f3964e  (AERO24_MODERATE_AGGRESSIVE_GAMING)",
                                             "stderr":  "",
                                             "error":  null,
                                             "started_at":  "2026-06-15T11:40:53",
                                             "completed_at":  "2026-06-15T11:40:53"
                                         }
                         },
                         {
                             "control_id":  "cpu.idle.disable",
                             "friendly_name":  "Processor idle disable",
                             "alias":  "IDLEDISABLE",
                             "setting_guid":  "5d76a2ca-e8c0-402f-a133-2158492d58ad",
                             "readable":  false,
                             "ac_value":  null,
                             "dc_value":  null,
                             "ac_hex":  null,
                             "dc_hex":  null,
                             "command":  {
                                             "name":  "powercfg_query_active_IDLEDISABLE",
                                             "command":  [
                                                             "powercfg.exe",
                                                             "/query",
                                                             "SCHEME_CURRENT",
                                                             "SUB_PROCESSOR",
                                                             "5d76a2ca-e8c0-402f-a133-2158492d58ad"
                                                         ],
                                             "exit_code":  0,
                                             "stdout_path":  "C:\\Users\\kkids\\Documents\\Codex_Computer_Optimizing\\AERO_X16_CONTROL_CENTER_APP\\PHASE_4_BACKUP_RESTORE_FOUNDATION_AND_SANDBOXED_APPLY_TESTS\\raw_outputs\\power_plan_backup\\powercfg_query_active_IDLEDISABLE_stdout.txt",
                                             "stderr_path":  "C:\\Users\\kkids\\Documents\\Codex_Computer_Optimizing\\AERO_X16_CONTROL_CENTER_APP\\PHASE_4_BACKUP_RESTORE_FOUNDATION_AND_SANDBOXED_APPLY_TESTS\\raw_outputs\\power_plan_backup\\powercfg_query_active_IDLEDISABLE_stderr.txt",
                                             "stdout":  "Power Scheme GUID: 692ee1d0-ffc2-4c47-91b3-2a4814f3964e  (AERO24_MODERATE_AGGRESSIVE_GAMING)",
                                             "stderr":  "",
                                             "error":  null,
                                             "started_at":  "2026-06-15T11:40:53",
                                             "completed_at":  "2026-06-15T11:40:53"
                                         }
                         },
                         {
                             "control_id":  "cpu.scheduling.heterogeneous_policy",
                             "friendly_name":  "Heterogeneous policy in effect",
                             "alias":  "HETEROPOLICY",
                             "setting_guid":  "7f2f5cfa-f10c-4823-b5e1-e93ae85f46b5",
                             "readable":  false,
                             "ac_value":  null,
                             "dc_value":  null,
                             "ac_hex":  null,
                             "dc_hex":  null,
                             "command":  {
                                             "name":  "powercfg_query_active_HETEROPOLICY",
                                             "command":  [
                                                             "powercfg.exe",
                                                             "/query",
                                                             "SCHEME_CURRENT",
                                                             "SUB_PROCESSOR",
                                                             "7f2f5cfa-f10c-4823-b5e1-e93ae85f46b5"
                                                         ],
                                             "exit_code":  0,
                                             "stdout_path":  "C:\\Users\\kkids\\Documents\\Codex_Computer_Optimizing\\AERO_X16_CONTROL_CENTER_APP\\PHASE_4_BACKUP_RESTORE_FOUNDATION_AND_SANDBOXED_APPLY_TESTS\\raw_outputs\\power_plan_backup\\powercfg_query_active_HETEROPOLICY_stdout.txt",
                                             "stderr_path":  "C:\\Users\\kkids\\Documents\\Codex_Computer_Optimizing\\AERO_X16_CONTROL_CENTER_APP\\PHASE_4_BACKUP_RESTORE_FOUNDATION_AND_SANDBOXED_APPLY_TESTS\\raw_outputs\\power_plan_backup\\powercfg_query_active_HETEROPOLICY_stderr.txt",
                                             "stdout":  "Power Scheme GUID: 692ee1d0-ffc2-4c47-91b3-2a4814f3964e  (AERO24_MODERATE_AGGRESSIVE_GAMING)",
                                             "stderr":  "",
                                             "error":  null,
                                             "started_at":  "2026-06-15T11:40:53",
                                             "completed_at":  "2026-06-15T11:40:53"
                                         }
                         },
                         {
                             "control_id":  "cpu.boost.performance_increase_threshold",
                             "friendly_name":  "Processor performance increase threshold",
                             "alias":  "PERFINCTHRESHOLD",
                             "setting_guid":  "06cadf0e-64ed-448a-8927-ce7bf90eb35d",
                             "readable":  false,
                             "ac_value":  null,
                             "dc_value":  null,
                             "ac_hex":  null,
                             "dc_hex":  null,
                             "command":  {
                                             "name":  "powercfg_query_active_PERFINCTHRESHOLD",
                                             "command":  [
                                                             "powercfg.exe",
                                                             "/query",
                                                             "SCHEME_CURRENT",
                                                             "SUB_PROCESSOR",
                                                             "06cadf0e-64ed-448a-8927-ce7bf90eb35d"
                                                         ],
                                             "exit_code":  0,
                                             "stdout_path":  "C:\\Users\\kkids\\Documents\\Codex_Computer_Optimizing\\AERO_X16_CONTROL_CENTER_APP\\PHASE_4_BACKUP_RESTORE_FOUNDATION_AND_SANDBOXED_APPLY_TESTS\\raw_outputs\\power_plan_backup\\powercfg_query_active_PERFINCTHRESHOLD_stdout.txt",
                                             "stderr_path":  "C:\\Users\\kkids\\Documents\\Codex_Computer_Optimizing\\AERO_X16_CONTROL_CENTER_APP\\PHASE_4_BACKUP_RESTORE_FOUNDATION_AND_SANDBOXED_APPLY_TESTS\\raw_outputs\\power_plan_backup\\powercfg_query_active_PERFINCTHRESHOLD_stderr.txt",
                                             "stdout":  "Power Scheme GUID: 692ee1d0-ffc2-4c47-91b3-2a4814f3964e  (AERO24_MODERATE_AGGRESSIVE_GAMING)",
                                             "stderr":  "",
                                             "error":  null,
                                             "started_at":  "2026-06-15T11:40:53",
                                             "completed_at":  "2026-06-15T11:40:53"
                                         }
                         },
                         {
                             "control_id":  "cpu.boost.performance_decrease_threshold",
                             "friendly_name":  "Processor performance decrease threshold",
                             "alias":  "PERFDECTHRESHOLD",
                             "setting_guid":  "12a0ab44-fe28-4fa9-b3bd-4b64f44960a6",
                             "readable":  false,
                             "ac_value":  null,
                             "dc_value":  null,
                             "ac_hex":  null,
                             "dc_hex":  null,
                             "command":  {
                                             "name":  "powercfg_query_active_PERFDECTHRESHOLD",
                                             "command":  [
                                                             "powercfg.exe",
                                                             "/query",
                                                             "SCHEME_CURRENT",
                                                             "SUB_PROCESSOR",
                                                             "12a0ab44-fe28-4fa9-b3bd-4b64f44960a6"
                                                         ],
                                             "exit_code":  0,
                                             "stdout_path":  "C:\\Users\\kkids\\Documents\\Codex_Computer_Optimizing\\AERO_X16_CONTROL_CENTER_APP\\PHASE_4_BACKUP_RESTORE_FOUNDATION_AND_SANDBOXED_APPLY_TESTS\\raw_outputs\\power_plan_backup\\powercfg_query_active_PERFDECTHRESHOLD_stdout.txt",
                                             "stderr_path":  "C:\\Users\\kkids\\Documents\\Codex_Computer_Optimizing\\AERO_X16_CONTROL_CENTER_APP\\PHASE_4_BACKUP_RESTORE_FOUNDATION_AND_SANDBOXED_APPLY_TESTS\\raw_outputs\\power_plan_backup\\powercfg_query_active_PERFDECTHRESHOLD_stderr.txt",
                                             "stdout":  "Power Scheme GUID: 692ee1d0-ffc2-4c47-91b3-2a4814f3964e  (AERO24_MODERATE_AGGRESSIVE_GAMING)",
                                             "stderr":  "",
                                             "error":  null,
                                             "started_at":  "2026-06-15T11:40:53",
                                             "completed_at":  "2026-06-15T11:40:53"
                                         }
                         }
                     ],
    "commands":  [
                     {
                         "name":  "powercfg_get_active_scheme",
                         "command":  [
                                         "powercfg.exe",
                                         "/getactivescheme"
                                     ],
                         "exit_code":  0,
                         "stdout_path":  "C:\\Users\\kkids\\Documents\\Codex_Computer_Optimizing\\AERO_X16_CONTROL_CENTER_APP\\PHASE_4_BACKUP_RESTORE_FOUNDATION_AND_SANDBOXED_APPLY_TESTS\\raw_outputs\\power_plan_backup\\powercfg_get_active_scheme_stdout.txt",
                         "stderr_path":  "C:\\Users\\kkids\\Documents\\Codex_Computer_Optimizing\\AERO_X16_CONTROL_CENTER_APP\\PHASE_4_BACKUP_RESTORE_FOUNDATION_AND_SANDBOXED_APPLY_TESTS\\raw_outputs\\power_plan_backup\\powercfg_get_active_scheme_stderr.txt",
                         "stdout":  "Power Scheme GUID: 692ee1d0-ffc2-4c47-91b3-2a4814f3964e  (AERO24_MODERATE_AGGRESSIVE_GAMING)",
                         "stderr":  "",
                         "error":  null,
                         "started_at":  "2026-06-15T11:40:52",
                         "completed_at":  "2026-06-15T11:40:52"
                     },
                     {
                         "name":  "powercfg_export_active_plan",
                         "command":  [
                                         "powercfg.exe",
                                         "/export",
                                         "C:\\Users\\kkids\\Documents\\Codex_Computer_Optimizing\\AERO_X16_CONTROL_CENTER_APP\\PHASE_4_BACKUP_RESTORE_FOUNDATION_AND_SANDBOXED_APPLY_TESTS\\backups\\power_plans\\active_power_plan_20260615-114052.pow",
                                         "692ee1d0-ffc2-4c47-91b3-2a4814f3964e"
                                     ],
                         "exit_code":  -1,
                         "stdout_path":  "C:\\Users\\kkids\\Documents\\Codex_Computer_Optimizing\\AERO_X16_CONTROL_CENTER_APP\\PHASE_4_BACKUP_RESTORE_FOUNDATION_AND_SANDBOXED_APPLY_TESTS\\raw_outputs\\power_plan_backup\\powercfg_export_active_plan_stdout.txt",
                         "stderr_path":  "C:\\Users\\kkids\\Documents\\Codex_Computer_Optimizing\\AERO_X16_CONTROL_CENTER_APP\\PHASE_4_BACKUP_RESTORE_FOUNDATION_AND_SANDBOXED_APPLY_TESTS\\raw_outputs\\power_plan_backup\\powercfg_export_active_plan_stderr.txt",
                         "stdout":  "",
                         "stderr":  "",
                         "error":  "Unable to perform operation.  An unexpected error (0x522) has occurred:  A required privilege is not held by the client.",
                         "started_at":  "2026-06-15T11:40:52",
                         "completed_at":  "2026-06-15T11:40:52"
                     },
                     {
                         "name":  "powercfg_query_scheme_current_full",
                         "command":  [
                                         "powercfg.exe",
                                         "/query",
                                         "SCHEME_CURRENT"
                                     ],
                         "exit_code":  0,
                         "stdout_path":  "C:\\Users\\kkids\\Documents\\Codex_Computer_Optimizing\\AERO_X16_CONTROL_CENTER_APP\\PHASE_4_BACKUP_RESTORE_FOUNDATION_AND_SANDBOXED_APPLY_TESTS\\raw_outputs\\power_plan_backup\\powercfg_query_scheme_current_full_stdout.txt",
                         "stderr_path":  "C:\\Users\\kkids\\Documents\\Codex_Computer_Optimizing\\AERO_X16_CONTROL_CENTER_APP\\PHASE_4_BACKUP_RESTORE_FOUNDATION_AND_SANDBOXED_APPLY_TESTS\\raw_outputs\\power_plan_backup\\powercfg_query_scheme_current_full_stderr.txt",
                         "stdout":  "Power Scheme GUID: 692ee1d0-ffc2-4c47-91b3-2a4814f3964e  (AERO24_MODERATE_AGGRESSIVE_GAMING)\r\n  Subgroup GUID: 0012ee47-9041-4b5d-9b77-535fba8b1442  (Hard disk)\r\n    GUID Alias: SUB_DISK\r\n    Power Setting GUID: 6738e2c4-e8a5-4a42-b16a-e040e769756e  (Turn off hard disk after)\r\n      GUID Alias: DISKIDLE\r\n      Minimum Possible Setting: 0x00000000\r\n      Maximum Possible Setting: 0xffffffff\r\n      Possible Settings increment: 0x00000001\r\n      Possible Settings units: Seconds\r\n    Current AC Power Setting Index: 0x00000000\r\n    Current DC Power Setting Index: 0x00000000\r\n\r\n  Subgroup GUID: 02f815b5-a5cf-4c84-bf20-649d1f75d3d8  (Internet Explorer)\r\n    Power Setting GUID: 4c793e7d-a264-42e1-87d3-7a0d2f523ccd  (JavaScript Timer Frequency)\r\n      Possible Setting Index: 000\r\n      Possible Setting Friendly Name: Maximum Power Savings\r\n      Possible Setting Index: 001\r\n      Possible Setting Friendly Name: Maximum Performance\r\n    Current AC Power Setting Index: 0x00000001\r\n    Current DC Power Setting Index: 0x00000001\r\n\r\n  Subgroup GUID: 0d7dbae2-4294-402a-ba8e-26777e8488cd  (Desktop background settings)\r\n    Power Setting GUID: 309dce9b-bef4-4119-9921-a851fb12f0f4  (Slide show)\r\n      Possible Setting Index: 000\r\n      Possible Setting Friendly Name: Available\r\n      Possible Setting Index: 001\r\n      Possible Setting Friendly Name: Paused\r\n    Current AC Power Setting Index: 0x00000000\r\n    Current DC Power Setting Index: 0x00000000\r\n\r\n  Subgroup GUID: 19cbb8fa-5279-450e-9fac-8a3d5fedd0c1  (Wireless Adapter Settings)\r\n    Power Setting GUID: 12bbebe6-58d6-4636-95bb-3217ef867c1a  (Power Saving Mode)\r\n      Possible Setting Index: 000\r\n      Possible Setting Friendly Name: Maximum Performance\r\n      Possible Setting Index: 001\r\n      Possible Setting Friendly Name: Low Power Saving\r\n      Possible Setting Index: 002\r\n      Possible Setting Friendly Name: Medium Power Saving\r\n      Possible Setting Index: 003\r\n      Possible Setting Friendly Name: Maximum Power Saving\r\n    Current AC Power Setting Index: 0x00000000\r\n    Current DC Power Setting Index: 0x00000000\r\n\r\n  Subgroup GUID: 238c9fa8-0aad-41ed-83f4-97be242c8f20  (Sleep)\r\n    GUID Alias: SUB_SLEEP\r\n    Power Setting GUID: 29f6c1db-86da-48c5-9fdb-f2b67b1f44da  (Sleep after)\r\n      GUID Alias: STANDBYIDLE\r\n      Minimum Possible Setting: 0x00000000\r\n      Maximum Possible Setting: 0xffffffff\r\n      Possible Settings increment: 0x00000001\r\n      Possible Settings units: Seconds\r\n    Current AC Power Setting Index: 0x00000258\r\n    Current DC Power Setting Index: 0x00000000\r\n\r\n    Power Setting GUID: 94ac6d29-73ce-41a6-809f-6363ba21b47e  (Allow hybrid sleep)\r\n      GUID Alias: HYBRIDSLEEP\r\n      Possible Setting Index: 000\r\n      Possible Setting Friendly Name: Off\r\n      Possible Setting Index: 001\r\n      Possible Setting Friendly Name: On\r\n    Current AC Power Setting Index: 0x00000001\r\n    Current DC Power Setting Index: 0x00000001\r\n\r\n    Power Setting GUID: 9d7815a6-7ee4-497e-8888-515a05f02364  (Hibernate after)\r\n      GUID Alias: HIBERNATEIDLE\r\n      Minimum Possible Setting: 0x00000000\r\n      Maximum Possible Setting: 0xffffffff\r\n      Possible Settings increment: 0x00000001\r\n      Possible Settings units: Seconds\r\n    Current AC Power Setting Index: 0x00000000\r\n    Current DC Power Setting Index: 0x00000000\r\n\r\n    Power Setting GUID: bd3b718a-0680-4d9d-8ab2-e1d2b4ac806d  (Allow wake timers)\r\n      GUID Alias: RTCWAKE\r\n      Possible Setting Index: 000\r\n      Possible Setting Friendly Name: Disable\r\n      Possible Setting Index: 001\r\n      Possible Setting Friendly Name: Enable\r\n      Possible Setting Index: 002\r\n      Possible Setting Friendly Name: Important Wake Timers Only\r\n    Current AC Power Setting Index: 0x00000000\r\n    Current DC Power Setting Index: 0x00000000\r\n\r\n  Subgroup GUID: 2a737441-1930-4402-8d77-b2bebba308a3  (USB settings)\r\n    Power Setting GUID: 48e6b7a6-50f5-4782-a5d4-53bb8f07e226  (USB selective suspend setting)\r\n      Possible Setting Index: 000\r\n      Possible Setting Friendly Name: Disabled\r\n      Possible Setting Index: 001\r\n      Possible Setting Friendly Name: Enabled\r\n    Current AC Power Setting Index: 0x00000001\r\n    Current DC Power Setting Index: 0x00000001\r\n\r\n  Subgroup GUID: 4f971e89-eebd-4455-a8de-9e59040e7347  (Power buttons and lid)\r\n    GUID Alias: SUB_BUTTONS\r\n    Power Setting GUID: a7066653-8d6c-40a8-910e-a1f54b84c7e5  (Start menu power button)\r\n      GUID Alias: UIBUTTON_ACTION\r\n      Possible Setting Index: 000\r\n      Possible Setting Friendly Name: Sleep\r\n      Possible Setting Index: 001\r\n      Possible Setting Friendly Name: Hibernate\r\n      Possible Setting Index: 002\r\n      Possible Setting Friendly Name: Shut down\r\n    Current AC Power Setting Index: 0x00000000\r\n    Current DC Power Setting Index: 0x00000000\r\n\r\n  Subgroup GUID: 501a4d13-42af-4429-9fd1-a8218c268e20  (PCI Express)\r\n    GUID Alias: SUB_PCIEXPRESS\r\n    Power Setting GUID: ee12f906-d277-404b-b6da-e5fa1a576df5  (Link State Power Management)\r\n      GUID Alias: ASPM\r\n      Possible Setting Index: 000\r\n      Possible Setting Friendly Name: Off\r\n      Possible Setting Index: 001\r\n      Possible Setting Friendly Name: Moderate power savings\r\n      Possible Setting Index: 002\r\n      Possible Setting Friendly Name: Maximum power savings\r\n    Current AC Power Setting Index: 0x00000000\r\n    Current DC Power Setting Index: 0x00000000\r\n\r\n  Subgroup GUID: 54533251-82be-4824-96c1-47b60b740d00  (Processor power management)\r\n    GUID Alias: SUB_PROCESSOR\r\n    Power Setting GUID: 36687f9e-e3a5-4dbf-b1dc-15eb381c6863  (Processor energy performance preference policy)\r\n      GUID Alias: PERFEPP\r\n      Minimum Possible Setting: 0x00000000\r\n      Maximum Possible Setting: 0x00000064\r\n      Possible Settings increment: 0x00000001\r\n      Possible Settings units: %\r\n    Current AC Power Setting Index: 0x00000037\r\n    Current DC Power Setting Index: 0x00000000\r\n\r\n    Power Setting GUID: 75b0ae3f-bce0-45a7-8c89-c9611c25e100  (Maximum processor frequency)\r\n      GUID Alias: PROCFREQMAX\r\n      Minimum Possible Setting: 0x00000000\r\n      Maximum Possible Setting: 0xffffffff\r\n      Possible Settings increment: 0x00000001\r\n      Possible Settings units: MHz\r\n    Current AC Power Setting Index: 0x00000cb2\r\n    Current DC Power Setting Index: 0x00000000\r\n\r\n    Power Setting GUID: 893dee8e-2bef-41e0-89c6-b55d0929964c  (Minimum processor state)\r\n      GUID Alias: PROCTHROTTLEMIN\r\n      Minimum Possible Setting: 0x00000000\r\n      Maximum Possible Setting: 0x00000064\r\n      Possible Settings increment: 0x00000001\r\n      Possible Settings units: %\r\n    Current AC Power Setting Index: 0x00000005\r\n    Current DC Power Setting Index: 0x00000064\r\n\r\n    Power Setting GUID: 94d3a615-a899-4ac5-ae2b-e4d8f634367f  (System cooling policy)\r\n      GUID Alias: SYSCOOLPOL\r\n      Possible Setting Index: 000\r\n      Possible Setting Friendly Name: Passive\r\n      Possible Setting Index: 001\r\n      Possible Setting Friendly Name: Active\r\n    Current AC Power Setting Index: 0x00000001\r\n    Current DC Power Setting Index: 0x00000001\r\n\r\n    Power Setting GUID: bc5038f7-23e0-4960-96da-33abaf5935ec  (Maximum processor state)\r\n      GUID Alias: PROCTHROTTLEMAX\r\n      Minimum Possible Setting: 0x00000000\r\n      Maximum Possible Setting: 0x00000064\r\n      Possible Settings increment: 0x00000001\r\n      Possible Settings units: %\r\n    Current AC Power Setting Index: 0x00000063\r\n    Current DC Power Setting Index: 0x00000064\r\n\r\n    Power Setting GUID: be337238-0d82-4146-a960-4f3749d470c7  (Processor performance boost mode)\r\n      GUID Alias: PERFBOOSTMODE\r\n      Possible Setting Index: 000\r\n      Possible Setting Friendly Name: Disabled\r\n      Possible Setting Index: 001\r\n      Possible Setting Friendly Name: Enabled\r\n      Possible Setting Index: 002\r\n      Possible Setting Friendly Name: Aggressive\r\n      Possible Setting Index: 003\r\n      Possible Setting Friendly Name: Efficient Enabled\r\n      Possible Setting Index: 004\r\n      Possible Setting Friendly Name: Efficient Aggressive\r\n      Possible Setting Index: 005\r\n      Possible Setting Friendly Name: Aggressive At Guaranteed\r\n      Possible Setting Index: 006\r\n      Possible Setting Friendly Name: Efficient Aggressive At Guaranteed\r\n    Current AC Power Setting Index: 0x00000000\r\n    Current DC Power Setting Index: 0x00000002\r\n\r\n  Subgroup GUID: 7516b95f-f776-4464-8c53-06167f40cc99  (Display)\r\n    GUID Alias: SUB_VIDEO\r\n    Power Setting GUID: 3c0bc021-c8a8-4e07-a973-6b14cbcb2b7e  (Turn off display after)\r\n      GUID Alias: VIDEOIDLE\r\n      Minimum Possible Setting: 0x00000000\r\n      Maximum Possible Setting: 0xffffffff\r\n      Possible Settings increment: 0x00000001\r\n      Possible Settings units: Seconds\r\n    Current AC Power Setting Index: 0x00000000\r\n    Current DC Power Setting Index: 0x00000000\r\n\r\n    Power Setting GUID: aded5e82-b909-4619-9949-f5d71dac0bcb  (Display brightness)\r\n      GUID Alias: VIDEONORMALLEVEL\r\n      Minimum Possible Setting: 0x00000000\r\n      Maximum Possible Setting: 0x00000064\r\n      Possible Settings increment: 0x00000001\r\n      Possible Settings units: %\r\n    Current AC Power Setting Index: 0x00000028\r\n    Current DC Power Setting Index: 0x00000028\r\n\r\n    Power Setting GUID: f1fbfde2-a960-4165-9f88-50667911ce96  (Dimmed display brightness)\r\n      Minimum Possible Setting: 0x00000000\r\n      Maximum Possible Setting: 0x00000064\r\n      Possible Settings increment: 0x00000001\r\n      Possible Settings units: %\r\n    Current AC Power Setting Index: 0x00000032\r\n    Current DC Power Setting Index: 0x00000032\r\n\r\n    Power Setting GUID: fbd9aa66-9553-4097-ba44-ed6e9d65eab8  (Enable adaptive brightness)\r\n      GUID Alias: ADAPTBRIGHT\r\n      Possible Setting Index: 000\r\n      Possible Setting Friendly Name: Off\r\n      Possible Setting Index: 001\r\n      Possible Setting Friendly Name: On\r\n    Current AC Power Setting Index: 0x00000000\r\n    Current DC Power Setting Index: 0x00000000\r\n\r\n  Subgroup GUID: 9596fb26-9850-41fd-ac3e-f7c3c00afd4b  (Multimedia settings)\r\n    Power Setting GUID: 03680956-93bc-4294-bba6-4e0f09bb717f  (When sharing media)\r\n      Possible Setting Index: 000\r\n      Possible Setting Friendly Name: Allow the computer to sleep\r\n      Possible Setting Index: 001\r\n      Possible Setting Friendly Name: Prevent idling to sleep\r\n      Possible Setting Index: 002\r\n      Possible Setting Friendly Name: Allow the computer to enter Away Mode\r\n    Current AC Power Setting Index: 0x00000001\r\n    Current DC Power Setting Index: 0x00000001\r\n\r\n    Power Setting GUID: 10778347-1370-4ee0-8bbd-33bdacaade49  (Video playback quality bias)\r\n      Possible Setting Index: 000\r\n      Possible Setting Friendly Name: Video playback power-saving bias\r\n      Possible Setting Index: 001\r\n      Possible Setting Friendly Name: Video playback performance bias\r\n    Current AC Power Setting Index: 0x00000001\r\n    Current DC Power Setting Index: 0x00000000\r\n\r\n    Power Setting GUID: 34c7b99f-9a6d-4b3c-8dc7-b6693b78cef4  (When playing video)\r\n      Possible Setting Index: 000\r\n      Possible Setting Friendly Name: Optimize video quality\r\n      Possible Setting Index: 001\r\n      Possible Setting Friendly Name: Balanced\r\n      Possible Setting Index: 002\r\n      Possible Setting Friendly Name: Optimize power savings\r\n    Current AC Power Setting Index: 0x00000000\r\n    Current DC Power Setting Index: 0x00000000\r\n\r\n  Subgroup GUID: c763b4ec-0e50-4b6b-9bed-2b92a6ee884e  (AMD Power Slider)\r\n    Power Setting GUID: 38cab4d5-db09-449f-9db5-1c91c909b6d4  (PMF Controller)\r\n    Current AC Power Setting Index: 0x00000002\r\n    Current DC Power Setting Index: 0x00000002\r\n\r\n    Power Setting GUID: 7ec1751b-60ed-4588-afb5-9819d3d77d90  (Overlay)\r\n      Possible Setting Index: 000\r\n      Possible Setting Friendly Name: Battery saver\r\n      Possible Setting Index: 001\r\n      Possible Setting Friendly Name: Better battery\r\n      Possible Setting Index: 002\r\n      Possible Setting Friendly Name: Better performance\r\n      Possible Setting Index: 003\r\n      Possible Setting Friendly Name: Best performance\r\n    Current AC Power Setting Index: 0x00000003\r\n    Current DC Power Setting Index: 0x00000003\r\n\r\n  Subgroup GUID: e276e160-7cb0-43c6-b20b-73f5dce39954  (Switchable Dynamic Graphics)\r\n    Power Setting GUID: a1662ab2-9d34-4e53-ba8b-2639b9e20857  (Global Settings)\r\n      Possible Setting Index: 000\r\n      Possible Setting Friendly Name: Force power-saving graphics\r\n      Possible Setting Index: 001\r\n      Possible Setting Friendly Name: Optimize power savings\r\n      Possible Setting Index: 002\r\n      Possible Setting Friendly Name: Optimize performance\r\n      Possible Setting Index: 003\r\n      Possible Setting Friendly Name: Maximize performance\r\n    Current AC Power Setting Index: 0x00000002\r\n    Current DC Power Setting Index: 0x00000001\r\n\r\n  Subgroup GUID: e73a048d-bf27-4f12-9731-8b2076e8891f  (Battery)\r\n    GUID Alias: SUB_BATTERY\r\n    Power Setting GUID: 5dbb7c9f-38e9-40d2-9749-4f8a0e9f640f  (Critical battery notification)\r\n      GUID Alias: BATFLAGSCRIT\r\n      Possible Setting Index: 000\r\n      Possible Setting Friendly Name: Off\r\n      Possible Setting Index: 001\r\n      Possible Setting Friendly Name: On\r\n    Current AC Power Setting Index: 0x00000001\r\n    Current DC Power Setting Index: 0x00000001\r\n\r\n    Power Setting GUID: 637ea02f-bbcb-4015-8e2c-a1c7b9c0b546  (Critical battery action)\r\n      GUID Alias: BATACTIONCRIT\r\n      Possible Setting Index: 000\r\n      Possible Setting Friendly Name: Do nothing\r\n      Possible Setting Index: 001\r\n      Possible Setting Friendly Name: Sleep\r\n      Possible Setting Index: 002\r\n      Possible Setting Friendly Name: Hibernate\r\n      Possible Setting Index: 003\r\n      Possible Setting Friendly Name: Shut down\r\n    Current AC Power Setting Index: 0x00000002\r\n    Current DC Power Setting Index: 0x00000002\r\n\r\n    Power Setting GUID: 8183ba9a-e910-48da-8769-14ae6dc1170a  (Low battery level)\r\n      GUID Alias: BATLEVELLOW\r\n      Minimum Possible Setting: 0x00000000\r\n      Maximum Possible Setting: 0x00000064\r\n      Possible Settings increment: 0x00000001\r\n      Possible Settings units: %\r\n    Current AC Power Setting Index: 0x00000006\r\n    Current DC Power Setting Index: 0x00000006\r\n\r\n    Power Setting GUID: 9a66d8d7-4ff7-4ef9-b5a2-5a326ca2a469  (Critical battery level)\r\n      GUID Alias: BATLEVELCRIT\r\n      Minimum Possible Setting: 0x00000000\r\n      Maximum Possible Setting: 0x00000064\r\n      Possible Settings increment: 0x00000001\r\n      Possible Settings units: %\r\n    Current AC Power Setting Index: 0x00000002\r\n    Current DC Power Setting Index: 0x00000002\r\n\r\n    Power Setting GUID: bcded951-187b-4d05-bccc-f7e51960c258  (Low battery notification)\r\n      GUID Alias: BATFLAGSLOW\r\n      Possible Setting Index: 000\r\n      Possible Setting Friendly Name: Off\r\n      Possible Setting Index: 001\r\n      Possible Setting Friendly Name: On\r\n    Current AC Power Setting Index: 0x00000001\r\n    Current DC Power Setting Index: 0x00000001\r\n\r\n    Power Setting GUID: d8742dcb-3e6a-4b3c-b3fe-374623cdcf06  (Low battery action)\r\n      GUID Alias: BATACTIONLOW\r\n      Possible Setting Index: 000\r\n      Possible Setting Friendly Name: Do nothing\r\n      Possible Setting Index: 001\r\n      Possible Setting Friendly Name: Sleep\r\n      Possible Setting Index: 002\r\n      Possible Setting Friendly Name: Hibernate\r\n      Possible Setting Index: 003\r\n      Possible Setting Friendly Name: Shut down\r\n    Current AC Power Setting Index: 0x00000000\r\n    Current DC Power Setting Index: 0x00000000\r\n\r\n    Power Setting GUID: f3c5027d-cd16-4930-aa6b-90db844a8f00  (Reserve battery level)\r\n      Minimum Possible Setting: 0x00000000\r\n      Maximum Possible Setting: 0x00000064\r\n      Possible Settings increment: 0x00000001\r\n      Possible Settings units: %\r\n    Current AC Power Setting Index: 0x00000004\r\n    Current DC Power Setting Index: 0x00000004",
                         "stderr":  "",
                         "error":  null,
                         "started_at":  "2026-06-15T11:40:52",
                         "completed_at":  "2026-06-15T11:40:52"
                     },
                     {
                         "name":  "powercfg_query_scheme_current_processor",
                         "command":  [
                                         "powercfg.exe",
                                         "/query",
                                         "SCHEME_CURRENT",
                                         "SUB_PROCESSOR"
                                     ],
                         "exit_code":  0,
                         "stdout_path":  "C:\\Users\\kkids\\Documents\\Codex_Computer_Optimizing\\AERO_X16_CONTROL_CENTER_APP\\PHASE_4_BACKUP_RESTORE_FOUNDATION_AND_SANDBOXED_APPLY_TESTS\\raw_outputs\\power_plan_backup\\powercfg_query_scheme_current_processor_stdout.txt",
                         "stderr_path":  "C:\\Users\\kkids\\Documents\\Codex_Computer_Optimizing\\AERO_X16_CONTROL_CENTER_APP\\PHASE_4_BACKUP_RESTORE_FOUNDATION_AND_SANDBOXED_APPLY_TESTS\\raw_outputs\\power_plan_backup\\powercfg_query_scheme_current_processor_stderr.txt",
                         "stdout":  "Power Scheme GUID: 692ee1d0-ffc2-4c47-91b3-2a4814f3964e  (AERO24_MODERATE_AGGRESSIVE_GAMING)\r\n  Subgroup GUID: 54533251-82be-4824-96c1-47b60b740d00  (Processor power management)\r\n    GUID Alias: SUB_PROCESSOR\r\n    Power Setting GUID: 36687f9e-e3a5-4dbf-b1dc-15eb381c6863  (Processor energy performance preference policy)\r\n      GUID Alias: PERFEPP\r\n      Minimum Possible Setting: 0x00000000\r\n      Maximum Possible Setting: 0x00000064\r\n      Possible Settings increment: 0x00000001\r\n      Possible Settings units: %\r\n    Current AC Power Setting Index: 0x00000037\r\n    Current DC Power Setting Index: 0x00000000\r\n\r\n    Power Setting GUID: 75b0ae3f-bce0-45a7-8c89-c9611c25e100  (Maximum processor frequency)\r\n      GUID Alias: PROCFREQMAX\r\n      Minimum Possible Setting: 0x00000000\r\n      Maximum Possible Setting: 0xffffffff\r\n      Possible Settings increment: 0x00000001\r\n      Possible Settings units: MHz\r\n    Current AC Power Setting Index: 0x00000cb2\r\n    Current DC Power Setting Index: 0x00000000\r\n\r\n    Power Setting GUID: 893dee8e-2bef-41e0-89c6-b55d0929964c  (Minimum processor state)\r\n      GUID Alias: PROCTHROTTLEMIN\r\n      Minimum Possible Setting: 0x00000000\r\n      Maximum Possible Setting: 0x00000064\r\n      Possible Settings increment: 0x00000001\r\n      Possible Settings units: %\r\n    Current AC Power Setting Index: 0x00000005\r\n    Current DC Power Setting Index: 0x00000064\r\n\r\n    Power Setting GUID: 94d3a615-a899-4ac5-ae2b-e4d8f634367f  (System cooling policy)\r\n      GUID Alias: SYSCOOLPOL\r\n      Possible Setting Index: 000\r\n      Possible Setting Friendly Name: Passive\r\n      Possible Setting Index: 001\r\n      Possible Setting Friendly Name: Active\r\n    Current AC Power Setting Index: 0x00000001\r\n    Current DC Power Setting Index: 0x00000001\r\n\r\n    Power Setting GUID: bc5038f7-23e0-4960-96da-33abaf5935ec  (Maximum processor state)\r\n      GUID Alias: PROCTHROTTLEMAX\r\n      Minimum Possible Setting: 0x00000000\r\n      Maximum Possible Setting: 0x00000064\r\n      Possible Settings increment: 0x00000001\r\n      Possible Settings units: %\r\n    Current AC Power Setting Index: 0x00000063\r\n    Current DC Power Setting Index: 0x00000064\r\n\r\n    Power Setting GUID: be337238-0d82-4146-a960-4f3749d470c7  (Processor performance boost mode)\r\n      GUID Alias: PERFBOOSTMODE\r\n      Possible Setting Index: 000\r\n      Possible Setting Friendly Name: Disabled\r\n      Possible Setting Index: 001\r\n      Possible Setting Friendly Name: Enabled\r\n      Possible Setting Index: 002\r\n      Possible Setting Friendly Name: Aggressive\r\n      Possible Setting Index: 003\r\n      Possible Setting Friendly Name: Efficient Enabled\r\n      Possible Setting Index: 004\r\n      Possible Setting Friendly Name: Efficient Aggressive\r\n      Possible Setting Index: 005\r\n      Possible Setting Friendly Name: Aggressive At Guaranteed\r\n      Possible Setting Index: 006\r\n      Possible Setting Friendly Name: Efficient Aggressive At Guaranteed\r\n    Current AC Power Setting Index: 0x00000000\r\n    Current DC Power Setting Index: 0x00000002",
                         "stderr":  "",
                         "error":  null,
                         "started_at":  "2026-06-15T11:40:52",
                         "completed_at":  "2026-06-15T11:40:53"
                     }
                 ]
}
