{
  "phase": "PHASE_3_CONTROL_SURFACE_COMPLETENESS_AND_PRESET_EDITING",
  "generated_local": "2026-06-15T03:18:02",
  "actions": [
    {
      "action_id": "read.powercfg.active_scheme",
      "friendly_name": "Read active power scheme",
      "category": "CPU power behavior",
      "phase3_status": "enabled_readonly",
      "risk": "Read-only",
      "command_template": "powercfg /getactivescheme",
      "backup_required": false,
      "restore_required": false,
      "ui_location": "CPU Presets",
      "validation_rule": "active scheme must parse"
    },
    {
      "action_id": "read.powercfg.cpu_setting",
      "friendly_name": "Read CPU power setting",
      "category": "CPU power behavior",
      "phase3_status": "enabled_readonly",
      "risk": "Read-only",
      "command_template": "powercfg /query <scheme_guid> SUB_PROCESSOR <setting_guid>",
      "backup_required": false,
      "restore_required": false,
      "ui_location": "CPU Presets",
      "validation_rule": "read result captured"
    },
    {
      "action_id": "preview.powercfg.set_cpu_setting",
      "friendly_name": "Preview CPU setting write",
      "category": "CPU power behavior",
      "phase3_status": "enabled_dryrun",
      "risk": "Medium",
      "command_template": "powercfg /setacvalueindex <scheme_guid> SUB_PROCESSOR <setting_guid> <value>",
      "backup_required": true,
      "restore_required": true,
      "ui_location": "CPU Presets",
      "validation_rule": "dry-run string only"
    },
    {
      "action_id": "future_apply.powercfg.set_cpu_setting",
      "friendly_name": "Future apply CPU setting",
      "category": "CPU power behavior",
      "phase3_status": "future",
      "risk": "Medium",
      "command_template": "powercfg /setacvalueindex <scheme_guid> SUB_PROCESSOR <setting_guid> <value>",
      "backup_required": true,
      "restore_required": true,
      "ui_location": "CPU Presets",
      "validation_rule": "blocked until restore proven"
    },
    {
      "action_id": "read.nvidia_smi.telemetry",
      "friendly_name": "Read NVIDIA telemetry",
      "category": "GPU power/clock telemetry",
      "phase3_status": "enabled_readonly",
      "risk": "Read-only",
      "command_template": "nvidia-smi --query-gpu=<fields> --format=csv,noheader,nounits",
      "backup_required": false,
      "restore_required": false,
      "ui_location": "Sensors / Telemetry",
      "validation_rule": "read-only query only"
    },
    {
      "action_id": "preview.msi.profile_slot",
      "friendly_name": "Preview MSI profile slot command",
      "category": "GPU profile loading",
      "phase3_status": "enabled_dryrun",
      "risk": "Medium",
      "command_template": "\"<MSIAfterburner.exe>\" -Profile<slot>",
      "backup_required": true,
      "restore_required": true,
      "ui_location": "GPU Profiles",
      "validation_rule": "dry-run string only"
    },
    {
      "action_id": "future_apply.msi.profile_slot",
      "friendly_name": "Future MSI profile launch",
      "category": "GPU profile loading",
      "phase3_status": "future",
      "risk": "Medium",
      "command_template": "\"<MSIAfterburner.exe>\" -Profile<slot>",
      "backup_required": true,
      "restore_required": true,
      "ui_location": "GPU Profiles",
      "validation_rule": "blocked until slot verified"
    },
    {
      "action_id": "future_backup.msi.configs",
      "friendly_name": "Future MSI config/profile backup",
      "category": "Restore/backup",
      "phase3_status": "future",
      "risk": "Low",
      "command_template": "Copy MSI config/profile files into restore manifest",
      "backup_required": false,
      "restore_required": true,
      "ui_location": "Settings / Safety",
      "validation_rule": "backup path stays inside app restore folder"
    },
    {
      "action_id": "future_backup.power_plan_export",
      "friendly_name": "Future power plan export",
      "category": "Restore/backup",
      "phase3_status": "future",
      "risk": "Safe",
      "command_template": "powercfg /export <file.pow> <scheme_guid>",
      "backup_required": false,
      "restore_required": true,
      "ui_location": "Settings / Safety",
      "validation_rule": "export before write"
    },
    {
      "action_id": "read.process.targets",
      "friendly_name": "Read process targets",
      "category": "Game detection",
      "phase3_status": "enabled_readonly",
      "risk": "Safe",
      "command_template": "Get-Process",
      "backup_required": false,
      "restore_required": false,
      "ui_location": "Game Automation",
      "validation_rule": "does not kill or modify processes"
    },
    {
      "action_id": "preview.automation.rule_match",
      "friendly_name": "Preview automation rule match",
      "category": "Game detection",
      "phase3_status": "preview_only",
      "risk": "Low",
      "command_template": "Compare running processes to app JSON rules",
      "backup_required": false,
      "restore_required": false,
      "ui_location": "Game Automation",
      "validation_rule": "preview only"
    },
    {
      "action_id": "future_apply.automation.enable_rule",
      "friendly_name": "Future automation enable rule",
      "category": "Startup automation",
      "phase3_status": "future",
      "risk": "Medium",
      "command_template": "App JSON and future task/startup plumbing",
      "backup_required": true,
      "restore_required": true,
      "ui_location": "Game Automation",
      "validation_rule": "blocked until restore and kill switch"
    },
    {
      "action_id": "read.presentmon.candidates",
      "friendly_name": "Read PresentMon candidates",
      "category": "FPS/frame capture",
      "phase3_status": "enabled_readonly",
      "risk": "Low",
      "command_template": "File metadata and optional help/version",
      "backup_required": false,
      "restore_required": false,
      "ui_location": "Sensors / Telemetry",
      "validation_rule": "timeout protected"
    },
    {
      "action_id": "future_capture.presentmon.session",
      "friendly_name": "Future PresentMon capture session",
      "category": "FPS/frame capture",
      "phase3_status": "future",
      "risk": "Low",
      "command_template": "PresentMon <verified args>",
      "backup_required": true,
      "restore_required": true,
      "ui_location": "Auto Tuning",
      "validation_rule": "blocked until syntax verified"
    },
    {
      "action_id": "blocked.fan.gcc_apply",
      "friendly_name": "Blocked GCC fan apply",
      "category": "Fan control",
      "phase3_status": "blocked",
      "risk": "High",
      "command_template": null,
      "backup_required": true,
      "restore_required": true,
      "ui_location": "Fan Control / Experimental",
      "validation_rule": "blocked"
    },
    {
      "action_id": "blocked.fan.ec_write",
      "friendly_name": "Blocked EC fan write",
      "category": "Experimental low-level hardware access",
      "phase3_status": "blocked",
      "risk": "Dangerous / Experimental",
      "command_template": null,
      "backup_required": true,
      "restore_required": true,
      "ui_location": "Fan Control / Experimental",
      "validation_rule": "blocked"
    }
  ]
}
